graphbook/__init__.py
graphbook/core/__init__.py
graphbook/core/cli.py
graphbook/core/clients.py
graphbook/core/config.py
graphbook/core/dataloading.py
graphbook/core/decorators.py
graphbook/core/doc2md.py
graphbook/core/logs/__init__.py
graphbook/core/logs/data.py
graphbook/core/logs/web.py
graphbook/core/media.py
graphbook/core/nodes.py
graphbook/core/note.py
graphbook/core/plugins.py
graphbook/core/processing/event_handler.py
graphbook/core/processing/graph_processor.py
graphbook/core/processing/graph_state.py
graphbook/core/processing/state.py
graphbook/core/processing/web_processor.py
graphbook/core/prompts.py
graphbook/core/resources/__init__.py
graphbook/core/resources/base.py
graphbook/core/sample_assets/SampleWorkflow.json
graphbook/core/sample_assets/SampleWorkflow.md
graphbook/core/sample_assets/sample_nodes.py
graphbook/core/serialization.py
graphbook/core/shm.py
graphbook/core/steps/__init__.py
graphbook/core/steps/base.py
graphbook/core/steps/io.py
graphbook/core/utils.py
graphbook/core/viewer.py
graphbook/core/web.py
graphbook/logging/__init__.py
graphbook/logging/torch.py
graphbook/ray/__init__.py
graphbook/ray/cli.py
graphbook/ray/ray_api.py
graphbook/ray/ray_client.py
graphbook/ray/ray_executor.py
graphbook/ray/ray_img.py
graphbook/ray/ray_processor.py
graphbook/ray/web.py
graphbook/web/assets/index-ATLzpucB.css
graphbook/web/assets/index-DyaK5nXC.js
graphbook/web/graphbook.svg
graphbook/web/index.html
graphbook-0.13.3.dist-info/LICENSE
graphbook-0.13.3.dist-info/METADATA
graphbook-0.13.3.dist-info/WHEEL
graphbook-0.13.3.dist-info/entry_points.txt
graphbook-0.13.3.dist-info/RECORD
