Metadata-Version: 2.3
Name: graphbook
Version: 0.13.3
Summary: The AI-driven data pipeline and workflow framework for data scientists and machine learning engineers.
License: MIT
Keywords: ml,workflow,framework,pytorch,data science,machine learning,ai
Author: Richard Franklin
Author-email: rsamf@graphbook.ai
Requires-Python: >=3.10,<4.0
Classifier: License :: OSI Approved :: MIT License
Classifier: Operating System :: OS Independent
Classifier: Programming Language :: Python :: 3
Classifier: Programming Language :: Python :: 3.10
Classifier: Programming Language :: Python :: 3.11
Classifier: Programming Language :: Python :: 3.12
Classifier: Programming Language :: Python :: 3.13
Provides-Extra: logging
Provides-Extra: ray
Requires-Dist: aiohttp (>=3.9.4,<4.0.0)
Requires-Dist: cloudpickle (>=3.1.1,<4.0.0)
Requires-Dist: msgpack (>=1.1.0,<2.0.0)
Requires-Dist: pillow (>=10.3.0,<11.0.0)
Requires-Dist: psutil (>=6.0.0,<7.0.0)
Requires-Dist: pyyaml (>=6.0.2,<7.0.0)
Requires-Dist: ray (>=2.41.0,<3.0.0) ; extra == "ray"
Requires-Dist: watchdog (>=4.0.0,<5.0.0)
Project-URL: Documentation, https://docs.graphbook.ai
Project-URL: Homepage, https://graphbook.ai
Project-URL: Repository, https://github.com/graphbookai/graphbook
